spotpapers/__init__.py
spotpapers/main.py
spotpapers/AI/groq.py
spotpapers-0.1.1.dist-info/LICENCE
spotpapers-0.1.1.dist-info/METADATA
spotpapers-0.1.1.dist-info/WHEEL
spotpapers-0.1.1.dist-info/entry_points.txt
spotpapers-0.1.1.dist-info/top_level.txt
spotpapers-0.1.1.dist-info/RECORD
