Metadata-Version: 2.1
Name: spotpapers
Version: 0.1.1
Summary: Simple CLI tool to get Windows spotlight wallpapers.
Author-email: Glitchy <advaith@glitchy.systems>
Classifier: Operating System :: Microsoft :: Windows
Classifier: Programming Language :: Python :: 3
Requires-Python: >=3.8
License-File: LICENCE
Requires-Dist: click
Requires-Dist: groq
Provides-Extra: dev
Requires-Dist: ruff; extra == "dev"
Requires-Dist: build; extra == "dev"
